{
    "id": "wendigo",
    "name": "Wendigo",
    "race": "cryptids",
    "type": "unit",
    "category": "melee",
    "description": "A gaunt, antlered horror driven by insatiable hunger. The Wendigo grows stronger with each kill, consuming the essence of its victims.",
    "stats": {
        "health": 600,
        "armor": 3,
        "damage": 28,
        "attackSpeed": 1.6,
        "moveSpeed": 290,
        "attackRange": 128
    },
    "costs": {
        "gold": 220,
        "lumber": 40,
        "essence": 25,
        "food": 3,
        "buildTime": 35.0
    },
    "sdfModel": {
        "name": "Wendigo",
        "bounds": {
            "min": [
                -0.7,
                0.7,
                -0.4
            ],
            "max": [
                0.7,
                2.0,
                0.4
            ]
        },
        "primitives": [
            {
                "id": "torso",
                "type": "Capsule",
                "params": {
                    "radius": 0.14,
                    "height": 0.47
                },
                "transform": {
                    "position": [
                        0.0,
                        1.2,
                        0.0
                    ],
                    "rotation": [
                        0.0,
                        0.0,
                        0.0,
                        1.0
                    ],
                    "scale": [
                        1.0,
                        1.0,
                        0.7
                    ]
                },
                "material": {
                    "baseColor": [
                        0.2,
                        0.18,
                        0.16,
                        1.0
                    ],
                    "metallic": 0.0,
                    "roughness": 0.9,
                    "subsurface": 0.45
                },
                "operation": "Union",
                "bone": "spine"
            },
            {
                "id": "ribs_visible",
                "type": "RoundedBox",
                "params": {
                    "size": [
                        0.16,
                        0.26,
                        0.09
                    ],
                    "radius": 0.025
                },
                "transform": {
                    "position": [
                        0.0,
                        1.25,
                        0.06
                    ],
                    "rotation": [
                        0.0,
                        0.0,
                        0.0,
                        1.0
                    ],
                    "scale": [
                        1.0,
                        1.0,
                        1.0
                    ]
                },
                "material": {
                    "baseColor": [
                        0.5,
                        0.48,
                        0.45,
                        1.0
                    ],
                    "metallic": 0.15,
                    "roughness": 0.8
                },
                "operation": "SmoothUnion",
                "smoothness": 0.03,
                "bone": "spine"
            },
            {
                "id": "pelvis",
                "type": "Ellipsoid",
                "params": {
                    "radii": [
                        0.12,
                        0.1,
                        0.08
                    ]
                },
                "transform": {
                    "position": [
                        0.0,
                        0.95,
                        0.0
                    ],
                    "rotation": [
                        0.0,
                        0.0,
                        0.0,
                        1.0
                    ],
                    "scale": [
                        1.0,
                        1.0,
                        1.0
                    ]
                },
                "material": {
                    "baseColor": [
                        0.2,
                        0.18,
                        0.16,
                        1.0
                    ],
                    "metallic": 0.0,
                    "roughness": 0.9,
                    "subsurface": 0.45
                },
                "operation": "SmoothUnion",
                "smoothness": 0.03,
                "bone": "spine"
            },
            {
                "id": "neck",
                "type": "Capsule",
                "params": {
                    "radius": 0.048,
                    "height": 0.2
                },
                "transform": {
                    "position": [
                        0.0,
                        1.55,
                        0.02
                    ],
                    "rotation": [
                        0.1,
                        0.0,
                        0.0,
                        0.995
                    ],
                    "scale": [
                        1.0,
                        1.0,
                        1.0
                    ]
                },
                "material": {
                    "baseColor": [
                        0.18,
                        0.16,
                        0.14,
                        1.0
                    ],
                    "metallic": 0.0,
                    "roughness": 0.85,
                    "subsurface": 0.45
                },
                "operation": "SmoothUnion",
                "smoothness": 0.02,
                "bone": "head"
            },
            {
                "id": "skull",
                "type": "Ellipsoid",
                "params": {
                    "radii": [
                        0.095,
                        0.115,
                        0.135
                    ]
                },
                "transform": {
                    "position": [
                        0.0,
                        1.75,
                        0.05
                    ],
                    "rotation": [
                        0.0,
                        0.0,
                        0.0,
                        1.0
                    ],
                    "scale": [
                        1.0,
                        1.0,
                        1.0
                    ]
                },
                "material": {
                    "baseColor": [
                        0.92,
                        0.87,
                        0.77,
                        1.0
                    ],
                    "metallic": 0.1,
                    "roughness": 0.6
                },
                "operation": "SmoothUnion",
                "smoothness": 0.02,
                "bone": "head"
            },
            {
                "id": "left_shoulder",
                "type": "Sphere",
                "params": {
                    "radius": 0.075
                },
                "transform": {
                    "position": [
                        0.2,
                        1.4,
                        0.0
                    ],
                    "rotation": [
                        0.0,
                        0.0,
                        0.0,
                        1.0
                    ],
                    "scale": [
                        1.0,
                        1.0,
                        1.0
                    ]
                },
                "material": {
                    "baseColor": [
                        0.2,
                        0.18,
                        0.16,
                        1.0
                    ],
                    "metallic": 0.0,
                    "roughness": 0.9,
                    "subsurface": 0.45
                },
                "operation": "Union",
                "bone": "clavicle_l"
            },
            {
                "id": "right_shoulder",
                "type": "Sphere",
                "params": {
                    "radius": 0.075
                },
                "transform": {
                    "position": [
                        -0.2,
                        1.4,
                        0.0
                    ],
                    "rotation": [
                        0.0,
                        0.0,
                        0.0,
                        1.0
                    ],
                    "scale": [
                        1.0,
                        1.0,
                        1.0
                    ]
                },
                "material": {
                    "baseColor": [
                        0.2,
                        0.18,
                        0.16,
                        1.0
                    ],
                    "metallic": 0.0,
                    "roughness": 0.9,
                    "subsurface": 0.45
                },
                "operation": "Union",
                "bone": "clavicle_r"
            },
            {
                "id": "left_upper_arm",
                "type": "Capsule",
                "params": {
                    "radius": 0.053,
                    "height": 0.32
                },
                "transform": {
                    "position": [
                        0.3,
                        1.2,
                        0.0
                    ],
                    "rotation": [
                        0.0,
                        0.0,
                        0.0,
                        1.0
                    ],
                    "scale": [
                        1.0,
                        1.0,
                        1.0
                    ]
                },
                "material": {
                    "baseColor": [
                        0.2,
                        0.18,
                        0.16,
                        1.0
                    ],
                    "metallic": 0.0,
                    "roughness": 0.9,
                    "subsurface": 0.45
                },
                "operation": "Union",
                "bone": "upperarm_l"
            },
            {
                "id": "right_upper_arm",
                "type": "Capsule",
                "params": {
                    "radius": 0.053,
                    "height": 0.32
                },
                "transform": {
                    "position": [
                        -0.3,
                        1.2,
                        0.0
                    ],
                    "rotation": [
                        0.0,
                        0.0,
                        0.0,
                        1.0
                    ],
                    "scale": [
                        1.0,
                        1.0,
                        1.0
                    ]
                },
                "material": {
                    "baseColor": [
                        0.2,
                        0.18,
                        0.16,
                        1.0
                    ],
                    "metallic": 0.0,
                    "roughness": 0.9,
                    "subsurface": 0.45
                },
                "operation": "Union",
                "bone": "upperarm_r"
            },
            {
                "id": "left_lower_arm",
                "type": "Capsule",
                "params": {
                    "radius": 0.048,
                    "height": 0.3
                },
                "transform": {
                    "position": [
                        0.4,
                        0.9,
                        0.0
                    ],
                    "rotation": [
                        0.0,
                        0.0,
                        0.0,
                        1.0
                    ],
                    "scale": [
                        1.0,
                        1.0,
                        1.0
                    ]
                },
                "material": {
                    "baseColor": [
                        0.2,
                        0.18,
                        0.16,
                        1.0
                    ],
                    "metallic": 0.0,
                    "roughness": 0.9,
                    "subsurface": 0.45
                },
                "operation": "Union",
                "bone": "lowerarm_l"
            },
            {
                "id": "right_lower_arm",
                "type": "Capsule",
                "params": {
                    "radius": 0.048,
                    "height": 0.3
                },
                "transform": {
                    "position": [
                        -0.4,
                        0.9,
                        0.0
                    ],
                    "rotation": [
                        0.0,
                        0.0,
                        0.0,
                        1.0
                    ],
                    "scale": [
                        1.0,
                        1.0,
                        1.0
                    ]
                },
                "material": {
                    "baseColor": [
                        0.2,
                        0.18,
                        0.16,
                        1.0
                    ],
                    "metallic": 0.0,
                    "roughness": 0.9,
                    "subsurface": 0.45
                },
                "operation": "Union",
                "bone": "lowerarm_r"
            },
            {
                "id": "left_hand",
                "type": "Sphere",
                "params": {
                    "radius": 0.06
                },
                "transform": {
                    "position": [
                        0.55,
                        0.65,
                        0.0
                    ],
                    "rotation": [
                        0.0,
                        0.0,
                        0.0,
                        1.0
                    ],
                    "scale": [
                        1.0,
                        1.0,
                        1.0
                    ]
                },
                "material": {
                    "baseColor": [
                        0.2,
                        0.18,
                        0.16,
                        1.0
                    ],
                    "metallic": 0.0,
                    "roughness": 0.9,
                    "subsurface": 0.45
                },
                "operation": "Union",
                "bone": "hand_l"
            },
            {
                "id": "right_hand",
                "type": "Sphere",
                "params": {
                    "radius": 0.06
                },
                "transform": {
                    "position": [
                        -0.55,
                        0.65,
                        0.0
                    ],
                    "rotation": [
                        0.0,
                        0.0,
                        0.0,
                        1.0
                    ],
                    "scale": [
                        1.0,
                        1.0,
                        1.0
                    ]
                },
                "material": {
                    "baseColor": [
                        0.2,
                        0.18,
                        0.16,
                        1.0
                    ],
                    "metallic": 0.0,
                    "roughness": 0.9,
                    "subsurface": 0.45
                },
                "operation": "Union",
                "bone": "hand_r"
            },
            {
                "id": "left_thigh",
                "type": "Capsule",
                "params": {
                    "radius": 0.07,
                    "height": 0.4
                },
                "transform": {
                    "position": [
                        0.15,
                        0.65,
                        0.0
                    ],
                    "rotation": [
                        0.0,
                        0.0,
                        0.0,
                        1.0
                    ],
                    "scale": [
                        1.0,
                        1.0,
                        1.0
                    ]
                },
                "material": {
                    "baseColor": [
                        0.2,
                        0.18,
                        0.16,
                        1.0
                    ],
                    "metallic": 0.0,
                    "roughness": 0.9,
                    "subsurface": 0.45
                },
                "operation": "Union",
                "bone": "thigh_l"
            },
            {
                "id": "right_thigh",
                "type": "Capsule",
                "params": {
                    "radius": 0.07,
                    "height": 0.4
                },
                "transform": {
                    "position": [
                        -0.15,
                        0.65,
                        0.0
                    ],
                    "rotation": [
                        0.0,
                        0.0,
                        0.0,
                        1.0
                    ],
                    "scale": [
                        1.0,
                        1.0,
                        1.0
                    ]
                },
                "material": {
                    "baseColor": [
                        0.2,
                        0.18,
                        0.16,
                        1.0
                    ],
                    "metallic": 0.0,
                    "roughness": 0.9,
                    "subsurface": 0.45
                },
                "operation": "Union",
                "bone": "thigh_r"
            },
            {
                "id": "left_shin",
                "type": "Capsule",
                "params": {
                    "radius": 0.06,
                    "height": 0.4
                },
                "transform": {
                    "position": [
                        0.15,
                        0.2,
                        0.0
                    ],
                    "rotation": [
                        0.0,
                        0.0,
                        0.0,
                        1.0
                    ],
                    "scale": [
                        1.0,
                        1.0,
                        1.0
                    ]
                },
                "material": {
                    "baseColor": [
                        0.2,
                        0.18,
                        0.16,
                        1.0
                    ],
                    "metallic": 0.0,
                    "roughness": 0.9,
                    "subsurface": 0.45
                },
                "operation": "Union",
                "bone": "shin_l"
            },
            {
                "id": "right_shin",
                "type": "Capsule",
                "params": {
                    "radius": 0.06,
                    "height": 0.4
                },
                "transform": {
                    "position": [
                        -0.15,
                        0.2,
                        0.0
                    ],
                    "rotation": [
                        0.0,
                        0.0,
                        0.0,
                        1.0
                    ],
                    "scale": [
                        1.0,
                        1.0,
                        1.0
                    ]
                },
                "material": {
                    "baseColor": [
                        0.2,
                        0.18,
                        0.16,
                        1.0
                    ],
                    "metallic": 0.0,
                    "roughness": 0.9,
                    "subsurface": 0.45
                },
                "operation": "Union",
                "bone": "shin_r"
            },
            {
                "id": "left_foot",
                "type": "Ellipsoid",
                "params": {
                    "radii": [
                        0.07,
                        0.04,
                        0.12
                    ]
                },
                "transform": {
                    "position": [
                        0.15,
                        -0.2,
                        0.05
                    ],
                    "rotation": [
                        0.0,
                        0.0,
                        0.0,
                        1.0
                    ],
                    "scale": [
                        1.0,
                        1.0,
                        1.0
                    ]
                },
                "material": {
                    "baseColor": [
                        0.2,
                        0.18,
                        0.16,
                        1.0
                    ],
                    "metallic": 0.0,
                    "roughness": 0.9,
                    "subsurface": 0.45
                },
                "operation": "Union",
                "bone": "foot_l"
            },
            {
                "id": "right_foot",
                "type": "Ellipsoid",
                "params": {
                    "radii": [
                        0.07,
                        0.04,
                        0.12
                    ]
                },
                "transform": {
                    "position": [
                        -0.15,
                        -0.2,
                        0.05
                    ],
                    "rotation": [
                        0.0,
                        0.0,
                        0.0,
                        1.0
                    ],
                    "scale": [
                        1.0,
                        1.0,
                        1.0
                    ]
                },
                "material": {
                    "baseColor": [
                        0.2,
                        0.18,
                        0.16,
                        1.0
                    ],
                    "metallic": 0.0,
                    "roughness": 0.9,
                    "subsurface": 0.45
                },
                "operation": "Union",
                "bone": "foot_r"
            },
            {
                "id": "antler_base_l",
                "type": "Sphere",
                "params": {
                    "radius": 0.04
                },
                "transform": {
                    "position": [
                        0.08,
                        1.85,
                        0.14
                    ],
                    "rotation": [
                        0.0,
                        0.0,
                        0.0,
                        1.0
                    ],
                    "scale": [
                        1.0,
                        1.0,
                        1.0
                    ]
                },
                "material": {
                    "baseColor": [
                        0.5,
                        0.45,
                        0.4,
                        1.0
                    ],
                    "metallic": 0.05,
                    "roughness": 0.7
                },
                "operation": "Union",
                "bone": "head"
            },
            {
                "id": "antler_base_r",
                "type": "Sphere",
                "params": {
                    "radius": 0.04
                },
                "transform": {
                    "position": [
                        -0.08,
                        1.85,
                        0.14
                    ],
                    "rotation": [
                        0.0,
                        0.0,
                        0.0,
                        1.0
                    ],
                    "scale": [
                        1.0,
                        1.0,
                        1.0
                    ]
                },
                "material": {
                    "baseColor": [
                        0.5,
                        0.45,
                        0.4,
                        1.0
                    ],
                    "metallic": 0.05,
                    "roughness": 0.7
                },
                "operation": "Union",
                "bone": "head"
            },
            {
                "id": "antler_branch_l1",
                "type": "Capsule",
                "params": {
                    "radius": 0.025,
                    "height": 0.2
                },
                "transform": {
                    "position": [
                        0.15,
                        1.95,
                        0.25
                    ],
                    "rotation": [
                        0.0,
                        0.2,
                        0.0,
                        0.98
                    ],
                    "scale": [
                        1.0,
                        1.0,
                        1.0
                    ]
                },
                "material": {
                    "baseColor": [
                        0.5,
                        0.45,
                        0.4,
                        1.0
                    ],
                    "metallic": 0.05,
                    "roughness": 0.7
                },
                "operation": "Union",
                "bone": "head"
            },
            {
                "id": "antler_branch_r1",
                "type": "Capsule",
                "params": {
                    "radius": 0.025,
                    "height": 0.2
                },
                "transform": {
                    "position": [
                        -0.15,
                        1.95,
                        0.25
                    ],
                    "rotation": [
                        0.0,
                        -0.2,
                        0.0,
                        0.98
                    ],
                    "scale": [
                        1.0,
                        1.0,
                        1.0
                    ]
                },
                "material": {
                    "baseColor": [
                        0.5,
                        0.45,
                        0.4,
                        1.0
                    ],
                    "metallic": 0.05,
                    "roughness": 0.7
                },
                "operation": "Union",
                "bone": "head"
            },
            {
                "id": "antler_branch_l2",
                "type": "Capsule",
                "params": {
                    "radius": 0.02,
                    "height": 0.15
                },
                "transform": {
                    "position": [
                        0.25,
                        2.05,
                        0.3
                    ],
                    "rotation": [
                        0.1,
                        0.3,
                        0.0,
                        0.95
                    ],
                    "scale": [
                        1.0,
                        1.0,
                        1.0
                    ]
                },
                "material": {
                    "baseColor": [
                        0.5,
                        0.45,
                        0.4,
                        1.0
                    ],
                    "metallic": 0.05,
                    "roughness": 0.7
                },
                "operation": "Union",
                "bone": "head"
            },
            {
                "id": "antler_branch_r2",
                "type": "Capsule",
                "params": {
                    "radius": 0.02,
                    "height": 0.15
                },
                "transform": {
                    "position": [
                        -0.25,
                        2.05,
                        0.3
                    ],
                    "rotation": [
                        -0.1,
                        -0.3,
                        0.0,
                        0.95
                    ],
                    "scale": [
                        1.0,
                        1.0,
                        1.0
                    ]
                },
                "material": {
                    "baseColor": [
                        0.5,
                        0.45,
                        0.4,
                        1.0
                    ],
                    "metallic": 0.05,
                    "roughness": 0.7
                },
                "operation": "Union",
                "bone": "head"
            },
            {
                "id": "scar_torso",
                "type": "RoundedBox",
                "params": {
                    "size": [
                        0.03,
                        0.1,
                        0.01
                    ],
                    "radius": 0.005
                },
                "transform": {
                    "position": [
                        0.05,
                        1.2,
                        0.1
                    ],
                    "rotation": [
                        0.0,
                        0.1,
                        0.0,
                        0.995
                    ],
                    "scale": [
                        1.0,
                        1.0,
                        1.0
                    ]
                },
                "material": {
                    "baseColor": [
                        0.4,
                        0.35,
                        0.3,
                        1.0
                    ],
                    "metallic": 0.0,
                    "roughness": 0.8,
                    "subsurface": 0.5
                },
                "operation": "SmoothSubtraction",
                "smoothness": 0.01,
                "bone": "spine"
            },
            {
                "id": "wear_mark_leg",
                "type": "RoundedBox",
                "params": {
                    "size": [
                        0.02,
                        0.08,
                        0.01
                    ],
                    "radius": 0.005
                },
                "transform": {
                    "position": [
                        -0.18,
                        0.2,
                        0.08
                    ],
                    "rotation": [
                        0.0,
                        -0.1,
                        0.0,
                        0.995
                    ],
                    "scale": [
                        1.0,
                        1.0,
                        1.0
                    ]
                },
                "material": {
                    "baseColor": [
                        0.15,
                        0.13,
                        0.12,
                        1.0
                    ],
                    "metallic": 0.0,
                    "roughness": 0.95
                },
                "operation": "SmoothSubtraction",
                "smoothness": 0.01,
                "bone": "shin_r"
            },
            {
                "id": "bone_necklace",
                "type": "Torus",
                "params": {
                    "radius": 0.18,
                    "tubeRadius": 0.02
                },
                "transform": {
                    "position": [
                        0.0,
                        1.45,
                        0.0
                    ],
                    "rotation": [
                        0.0,
                        0.0,
                        0.0,
                        1.0
                    ],
                    "scale": [
                        1.0,
                        1.0,
                        1.0
                    ]
                },
                "material": {
                    "baseColor": [
                        0.85,
                        0.8,
                        0.7,
                        1.0
                    ],
                    "metallic": 0.05,
                    "roughness": 0.6
                },
                "operation": "Union",
                "bone": "spine"
            },
            {
                "id": "emissive_eyes",
                "type": "Sphere",
                "params": {
                    "radius": 0.02
                },
                "transform": {
                    "position": [
                        0.04,
                        1.77,
                        0.15
                    ],
                    "rotation": [
                        0.0,
                        0.0,
                        0.0,
                        1.0
                    ],
                    "scale": [
                        1.0,
                        1.0,
                        1.0
                    ]
                },
                "material": {
                    "baseColor": [
                        1,
                        1,
                        1,
                        1.0
                    ],
                    "metallic": 0.0,
                    "roughness": 0.6,
                    "emissive": [
                        2,
                        0.5,
                        0.5
                    ]
                },
                "operation": "Union",
                "bone": "head"
            },
            {
                "id": "emissive_eyes2",
                "type": "Sphere",
                "params": {
                    "radius": 0.02
                },
                "transform": {
                    "position": [
                        -0.04,
                        1.77,
                        0.15
                    ],
                    "rotation": [
                        0.0,
                        0.0,
                        0.0,
                        1.0
                    ],
                    "scale": [
                        1.0,
                        1.0,
                        1.0
                    ]
                },
                "material": {
                    "baseColor": [
                        1,
                        1,
                        1,
                        1.0
                    ],
                    "metallic": 0.0,
                    "roughness": 0.6,
                    "emissive": [
                        2,
                        0.5,
                        0.5
                    ]
                },
                "operation": "Union",
                "bone": "head"
            }
        ]
    },
    "skeleton": {
        "bones": [
            {
                "name": "root",
                "parent": null,
                "position": [
                    0.0,
                    0.0,
                    0.0
                ],
                "rotation": [
                    0.0,
                    0.0,
                    0.0,
                    1.0
                ]
            },
            {
                "name": "spine",
                "parent": "root",
                "position": [
                    0.0,
                    0.95,
                    0.0
                ],
                "rotation": [
                    0.0,
                    0.0,
                    0.0,
                    1.0
                ]
            },
            {
                "name": "head",
                "parent": "spine",
                "position": [
                    0.0,
                    0.5,
                    0.02
                ],
                "rotation": [
                    0.0,
                    0.0,
                    0.0,
                    1.0
                ]
            },
            {
                "name": "arm_l",
                "parent": "spine",
                "position": [
                    -0.14,
                    0.35,
                    0.0
                ],
                "rotation": [
                    0.0,
                    0.0,
                    0.15,
                    0.99
                ]
            },
            {
                "name": "arm_r",
                "parent": "spine",
                "position": [
                    0.14,
                    0.35,
                    0.0
                ],
                "rotation": [
                    0.0,
                    0.0,
                    -0.15,
                    0.99
                ]
            },
            {
                "name": "leg_l",
                "parent": "root",
                "position": [
                    -0.08,
                    0.85,
                    0.0
                ],
                "rotation": [
                    0.0,
                    0.0,
                    0.0,
                    1.0
                ]
            },
            {
                "name": "leg_r",
                "parent": "root",
                "position": [
                    0.08,
                    0.85,
                    0.0
                ],
                "rotation": [
                    0.0,
                    0.0,
                    0.0,
                    1.0
                ]
            }
        ]
    },
    "animations": {
        "idle": {
            "duration": 3.0,
            "loop": true,
            "keyframes": [
                {
                    "time": 0.0,
                    "bones": {
                        "spine": {
                            "rotation": [
                                0.0,
                                0.0,
                                0.0,
                                1.0
                            ]
                        },
                        "head": {
                            "rotation": [
                                0.0,
                                0.0,
                                0.0,
                                1.0
                            ]
                        }
                    }
                },
                {
                    "time": 1.0,
                    "bones": {
                        "spine": {
                            "rotation": [
                                0.02,
                                0.0,
                                0.0,
                                0.9998
                            ]
                        },
                        "head": {
                            "rotation": [
                                -0.05,
                                0.1,
                                0.0,
                                0.99
                            ]
                        }
                    }
                },
                {
                    "time": 2.0,
                    "bones": {
                        "spine": {
                            "rotation": [
                                0.0,
                                0.0,
                                0.0,
                                1.0
                            ]
                        },
                        "head": {
                            "rotation": [
                                -0.05,
                                -0.1,
                                0.0,
                                0.99
                            ]
                        }
                    }
                },
                {
                    "time": 3.0,
                    "bones": {
                        "spine": {
                            "rotation": [
                                0.0,
                                0.0,
                                0.0,
                                1.0
                            ]
                        },
                        "head": {
                            "rotation": [
                                0.0,
                                0.0,
                                0.0,
                                1.0
                            ]
                        }
                    }
                }
            ]
        },
        "walk": {
            "duration": 0.8,
            "loop": true,
            "keyframes": [
                {
                    "time": 0.0,
                    "bones": {
                        "root": {
                            "position": [
                                0.0,
                                0.0,
                                0.0
                            ]
                        },
                        "leg_l": {
                            "rotation": [
                                0.3,
                                0.0,
                                0.0,
                                0.95
                            ]
                        },
                        "leg_r": {
                            "rotation": [
                                -0.3,
                                0.0,
                                0.0,
                                0.95
                            ]
                        },
                        "arm_l": {
                            "rotation": [
                                -0.15,
                                0.0,
                                0.15,
                                0.97
                            ]
                        },
                        "arm_r": {
                            "rotation": [
                                0.15,
                                0.0,
                                -0.15,
                                0.97
                            ]
                        }
                    }
                },
                {
                    "time": 0.2,
                    "bones": {
                        "root": {
                            "position": [
                                0.0,
                                0.03,
                                0.0
                            ]
                        }
                    }
                },
                {
                    "time": 0.4,
                    "bones": {
                        "root": {
                            "position": [
                                0.0,
                                0.0,
                                0.0
                            ]
                        },
                        "leg_l": {
                            "rotation": [
                                -0.3,
                                0.0,
                                0.0,
                                0.95
                            ]
                        },
                        "leg_r": {
                            "rotation": [
                                0.3,
                                0.0,
                                0.0,
                                0.95
                            ]
                        },
                        "arm_l": {
                            "rotation": [
                                0.15,
                                0.0,
                                0.15,
                                0.97
                            ]
                        },
                        "arm_r": {
                            "rotation": [
                                -0.15,
                                0.0,
                                -0.15,
                                0.97
                            ]
                        }
                    }
                },
                {
                    "time": 0.6,
                    "bones": {
                        "root": {
                            "position": [
                                0.0,
                                0.03,
                                0.0
                            ]
                        }
                    }
                },
                {
                    "time": 0.8,
                    "bones": {
                        "root": {
                            "position": [
                                0.0,
                                0.0,
                                0.0
                            ]
                        },
                        "leg_l": {
                            "rotation": [
                                0.3,
                                0.0,
                                0.0,
                                0.95
                            ]
                        },
                        "leg_r": {
                            "rotation": [
                                -0.3,
                                0.0,
                                0.0,
                                0.95
                            ]
                        },
                        "arm_l": {
                            "rotation": [
                                -0.15,
                                0.0,
                                0.15,
                                0.97
                            ]
                        },
                        "arm_r": {
                            "rotation": [
                                0.15,
                                0.0,
                                -0.15,
                                0.97
                            ]
                        }
                    }
                }
            ]
        },
        "attack": {
            "duration": 1.0,
            "loop": false,
            "keyframes": [
                {
                    "time": 0.0,
                    "bones": {
                        "spine": {
                            "rotation": [
                                0.0,
                                -0.15,
                                0.0,
                                0.99
                            ]
                        },
                        "arm_l": {
                            "rotation": [
                                -0.3,
                                0.0,
                                -0.4,
                                0.86
                            ]
                        },
                        "arm_r": {
                            "rotation": [
                                -0.3,
                                0.0,
                                0.4,
                                0.86
                            ]
                        }
                    }
                },
                {
                    "time": 0.3,
                    "bones": {
                        "spine": {
                            "rotation": [
                                -0.1,
                                -0.2,
                                0.0,
                                0.97
                            ]
                        },
                        "arm_l": {
                            "rotation": [
                                -0.5,
                                0.0,
                                -0.5,
                                0.71
                            ]
                        },
                        "arm_r": {
                            "rotation": [
                                -0.5,
                                0.0,
                                0.5,
                                0.71
                            ]
                        }
                    }
                },
                {
                    "time": 0.5,
                    "bones": {
                        "spine": {
                            "rotation": [
                                0.15,
                                0.15,
                                0.0,
                                0.97
                            ]
                        },
                        "arm_l": {
                            "rotation": [
                                0.4,
                                0.0,
                                -0.3,
                                0.87
                            ]
                        },
                        "arm_r": {
                            "rotation": [
                                0.4,
                                0.0,
                                0.3,
                                0.87
                            ]
                        }
                    },
                    "events": [
                        "claw_slash"
                    ]
                },
                {
                    "time": 1.0,
                    "bones": {
                        "spine": {
                            "rotation": [
                                0.0,
                                0.0,
                                0.0,
                                1.0
                            ]
                        },
                        "arm_l": {
                            "rotation": [
                                0.0,
                                0.0,
                                0.15,
                                0.99
                            ]
                        },
                        "arm_r": {
                            "rotation": [
                                0.0,
                                0.0,
                                -0.15,
                                0.99
                            ]
                        }
                    }
                }
            ]
        },
        "consume": {
            "duration": 2.0,
            "loop": false,
            "keyframes": [
                {
                    "time": 0.0,
                    "bones": {
                        "spine": {
                            "rotation": [
                                0.2,
                                0.0,
                                0.0,
                                0.98
                            ]
                        },
                        "head": {
                            "rotation": [
                                0.3,
                                0.0,
                                0.0,
                                0.95
                            ]
                        }
                    }
                },
                {
                    "time": 0.5,
                    "bones": {
                        "spine": {
                            "rotation": [
                                0.4,
                                0.0,
                                0.0,
                                0.92
                            ]
                        },
                        "head": {
                            "rotation": [
                                0.5,
                                0.0,
                                0.0,
                                0.87
                            ]
                        }
                    },
                    "events": [
                        "consume_start"
                    ]
                },
                {
                    "time": 1.5,
                    "bones": {
                        "spine": {
                            "rotation": [
                                0.3,
                                0.0,
                                0.0,
                                0.95
                            ]
                        },
                        "head": {
                            "rotation": [
                                0.4,
                                0.0,
                                0.0,
                                0.92
                            ]
                        }
                    }
                },
                {
                    "time": 2.0,
                    "bones": {
                        "spine": {
                            "rotation": [
                                0.0,
                                0.0,
                                0.0,
                                1.0
                            ]
                        },
                        "head": {
                            "rotation": [
                                0.0,
                                0.0,
                                0.0,
                                1.0
                            ]
                        }
                    },
                    "events": [
                        "consume_end"
                    ]
                }
            ]
        },
        "frenzy": {
            "duration": 1.5,
            "loop": true,
            "keyframes": [
                {
                    "time": 0.0,
                    "bones": {
                        "spine": {
                            "rotation": [
                                0.0,
                                0.0,
                                0.0,
                                1.0
                            ]
                        },
                        "arm_l": {
                            "rotation": [
                                -0.4,
                                0.0,
                                -0.4,
                                0.82
                            ]
                        },
                        "arm_r": {
                            "rotation": [
                                -0.4,
                                0.0,
                                0.4,
                                0.82
                            ]
                        }
                    }
                },
                {
                    "time": 0.25,
                    "bones": {
                        "spine": {
                            "rotation": [
                                0.1,
                                0.1,
                                0.0,
                                0.99
                            ]
                        },
                        "arm_l": {
                            "rotation": [
                                0.3,
                                0.0,
                                -0.3,
                                0.9
                            ]
                        },
                        "arm_r": {
                            "rotation": [
                                -0.4,
                                0.0,
                                0.4,
                                0.82
                            ]
                        }
                    },
                    "events": [
                        "frenzy_slash"
                    ]
                },
                {
                    "time": 0.5,
                    "bones": {
                        "spine": {
                            "rotation": [
                                0.0,
                                0.0,
                                0.0,
                                1.0
                            ]
                        },
                        "arm_l": {
                            "rotation": [
                                -0.4,
                                0.0,
                                -0.4,
                                0.82
                            ]
                        },
                        "arm_r": {
                            "rotation": [
                                -0.4,
                                0.0,
                                0.4,
                                0.82
                            ]
                        }
                    }
                },
                {
                    "time": 0.75,
                    "bones": {
                        "spine": {
                            "rotation": [
                                0.1,
                                -0.1,
                                0.0,
                                0.99
                            ]
                        },
                        "arm_l": {
                            "rotation": [
                                -0.4,
                                0.0,
                                -0.4,
                                0.82
                            ]
                        },
                        "arm_r": {
                            "rotation": [
                                0.3,
                                0.0,
                                0.3,
                                0.9
                            ]
                        }
                    },
                    "events": [
                        "frenzy_slash"
                    ]
                },
                {
                    "time": 1.0,
                    "bones": {
                        "spine": {
                            "rotation": [
                                0.0,
                                0.0,
                                0.0,
                                1.0
                            ]
                        }
                    }
                },
                {
                    "time": 1.5,
                    "bones": {
                        "spine": {
                            "rotation": [
                                0.0,
                                0.0,
                                0.0,
                                1.0
                            ]
                        },
                        "arm_l": {
                            "rotation": [
                                -0.4,
                                0.0,
                                -0.4,
                                0.82
                            ]
                        },
                        "arm_r": {
                            "rotation": [
                                -0.4,
                                0.0,
                                0.4,
                                0.82
                            ]
                        }
                    }
                }
            ]
        },
        "death": {
            "duration": 1.5,
            "loop": false,
            "keyframes": [
                {
                    "time": 0.0,
                    "bones": {
                        "root": {
                            "position": [
                                0.0,
                                0.0,
                                0.0
                            ],
                            "rotation": [
                                0.0,
                                0.0,
                                0.0,
                                1.0
                            ]
                        }
                    }
                },
                {
                    "time": 0.4,
                    "bones": {
                        "root": {
                            "position": [
                                0.0,
                                -0.2,
                                0.0
                            ],
                            "rotation": [
                                0.15,
                                0.0,
                                0.15,
                                0.97
                            ]
                        },
                        "spine": {
                            "rotation": [
                                -0.2,
                                0.0,
                                0.0,
                                0.98
                            ]
                        }
                    }
                },
                {
                    "time": 0.8,
                    "bones": {
                        "root": {
                            "position": [
                                0.0,
                                -0.5,
                                0.15
                            ],
                            "rotation": [
                                0.4,
                                0.0,
                                0.2,
                                0.89
                            ]
                        }
                    }
                },
                {
                    "time": 1.5,
                    "bones": {
                        "root": {
                            "position": [
                                0.0,
                                -0.8,
                                0.25
                            ],
                            "rotation": [
                                0.6,
                                0.0,
                                0.2,
                                0.77
                            ]
                        }
                    }
                }
            ]
        }
    },
    "animationStateMachine": {
        "initialState": "idle",
        "states": {
            "idle": {
                "animation": "idle",
                "transitions": [
                    {
                        "to": "walk",
                        "condition": "isMoving"
                    },
                    {
                        "to": "attack",
                        "condition": "isAttacking"
                    },
                    {
                        "to": "consume",
                        "condition": "isConsuming"
                    },
                    {
                        "to": "frenzy",
                        "condition": "isFrenzied"
                    },
                    {
                        "to": "death",
                        "condition": "isDead"
                    }
                ]
            },
            "walk": {
                "animation": "walk",
                "transitions": [
                    {
                        "to": "idle",
                        "condition": "!isMoving"
                    },
                    {
                        "to": "attack",
                        "condition": "isAttacking"
                    },
                    {
                        "to": "frenzy",
                        "condition": "isFrenzied"
                    },
                    {
                        "to": "death",
                        "condition": "isDead"
                    }
                ]
            },
            "attack": {
                "animation": "attack",
                "transitions": [
                    {
                        "to": "idle",
                        "condition": "animationComplete && !isMoving"
                    },
                    {
                        "to": "walk",
                        "condition": "animationComplete && isMoving"
                    },
                    {
                        "to": "frenzy",
                        "condition": "isFrenzied"
                    },
                    {
                        "to": "death",
                        "condition": "isDead"
                    }
                ]
            },
            "consume": {
                "animation": "consume",
                "transitions": [
                    {
                        "to": "idle",
                        "condition": "animationComplete"
                    },
                    {
                        "to": "death",
                        "condition": "isDead"
                    }
                ]
            },
            "frenzy": {
                "animation": "frenzy",
                "transitions": [
                    {
                        "to": "idle",
                        "condition": "!isFrenzied && !isMoving"
                    },
                    {
                        "to": "walk",
                        "condition": "!isFrenzied && isMoving"
                    },
                    {
                        "to": "death",
                        "condition": "isDead"
                    }
                ]
            },
            "death": {
                "animation": "death",
                "transitions": []
            }
        }
    },
    "abilities": [
        {
            "id": "consume",
            "name": "Consume",
            "description": "Devours a corpse to heal and permanently gain stats.",
            "hotkey": "C",
            "cooldown": 10.0
        },
        {
            "id": "ravenous_frenzy",
            "name": "Ravenous Frenzy",
            "description": "Enters a bloodthirsty state, gaining attack speed but losing armor.",
            "hotkey": "F",
            "cooldown": 30.0
        },
        {
            "id": "freezing_aura",
            "name": "Freezing Aura",
            "description": "Nearby enemies are slowed by supernatural cold.",
            "isPassive": true
        },
        {
            "id": "hunger_grows",
            "name": "Hunger Grows",
            "description": "Gains bonus damage and health for each kill.",
            "isPassive": true
        }
    ],
    "behaviors": {
        "on_spawn": {
            "actions": [
                {
                    "type": "play_sound",
                    "sound": "wendigo_ready"
                },
                {
                    "type": "random_say",
                    "texts": [
                        "*hungry howl*",
                        "*ravenous growl*",
                        "*icy breath*"
                    ],
                    "chance": 1.0
                }
            ]
        },
        "on_attack": {
            "actions": [
                {
                    "type": "play_animation",
                    "animation": "attack"
                },
                {
                    "type": "play_sound",
                    "sound": "wendigo_attack"
                }
            ]
        },
        "on_death": {
            "actions": [
                {
                    "type": "play_animation",
                    "animation": "death"
                },
                {
                    "type": "play_sound",
                    "sound": "wendigo_death"
                }
            ]
        }
    }
}