{
    "id": "ability_mech_summon",
    "name": "Mech Summon",
    "description": "Summon a powerful combat mech that fights alongside you.",
    "type": "active",
    "max_level": 3,
    "targeting": "point",

    "levels": [
        {"mana_cost": 150, "cooldown": 100, "duration": 40, "range": 5, "damage": 60, "special_value_1": 1200, "special_value_2": 8},
        {"mana_cost": 200, "cooldown": 90, "duration": 50, "range": 5, "damage": 90, "special_value_1": 1800, "special_value_2": 12},
        {"mana_cost": 250, "cooldown": 80, "duration": 60, "range": 5, "damage": 120, "special_value_1": 2400, "special_value_2": 16}
    ],

    "effects": {
        "cast_sound": "sounds/abilities/mech_summon.wav",
        "cast_particle": "effects/mech_arrive.fx",
        "icon": "textures/abilities/mech_summon.png"
    },

    "scripts": {
        "on_cast_complete": "scripts/abilities/mech_summon.py"
    },

    "tags": ["active", "ultimate", "summon", "point_target"]
}
