{
    "id": "death_knight",
    "name": "Death Knight",
    "race": "undead",
    "type": "hero",
    "category": "melee",
    "description": "A fallen paladin corrupted by dark powers. Commands death magic and wields a massive runeblade infused with unholy energy.",

    "stats": {
        "health": 675,
        "mana": 270,
        "armor": 4,
        "damage": 32,
        "attackSpeed": 1.6,
        "moveSpeed": 320,
        "attackRange": 120,
        "healthPerLevel": 100,
        "manaPerLevel": 25,
        "damagePerLevel": 4,
        "armorPerLevel": 0.5
    },

    "costs": {
        "gold": 500,
        "food": 5,
        "buildTime": 55.0
    },

    "sdfModel": {
        "name": "death_knight_model",
        "bounds": { "min": [-0.6, 0.0, -0.6], "max": [0.6, 2.2, 0.6] },
        "primitives": [
            {
                "id": "torso",
                "type": "RoundedBox",
                "params": { "size": [0.28, 0.32, 0.18], "radius": 0.05 },
                "transform": { "position": [0.0, 1.25, 0.0], "rotation": [0.0, 0.0, 0.0, 1.0], "scale": [1.0, 1.0, 1.0] },
                "material": { "baseColor": [0.08, 0.08, 0.1, 1.0], "metallic": 0.9, "roughness": 0.3 },
                "operation": "Union"
            },
            {
                "id": "armor_chest_runes",
                "type": "RoundedBox",
                "params": { "size": [0.22, 0.15, 0.02], "radius": 0.01 },
                "transform": { "position": [0.0, 1.3, 0.1], "rotation": [0.0, 0.0, 0.0, 1.0], "scale": [1.0, 1.0, 1.0] },
                "material": { "baseColor": [0.2, 0.5, 0.8, 1.0], "metallic": 0.0, "roughness": 0.1, "emissive": [0.1, 0.25, 0.4] },
                "operation": "Union"
            },
            {
                "id": "waist",
                "type": "Capsule",
                "params": { "radius": 0.12, "height": 0.15 },
                "transform": { "position": [0.0, 1.0, 0.0], "rotation": [0.0, 0.0, 0.0, 1.0], "scale": [1.0, 1.0, 0.85] },
                "material": { "baseColor": [0.1, 0.08, 0.05, 1.0], "metallic": 0.4, "roughness": 0.6 },
                "operation": "SmoothUnion",
                "smoothness": 0.03
            },
            {
                "id": "belt",
                "type": "Torus",
                "params": { "majorRadius": 0.13, "minorRadius": 0.03 },
                "transform": { "position": [0.0, 1.0, 0.0], "rotation": [0.0, 0.0, 0.0, 1.0], "scale": [1.0, 0.4, 1.0] },
                "material": { "baseColor": [0.6, 0.5, 0.1, 1.0], "metallic": 0.85, "roughness": 0.25 },
                "operation": "Union"
            },
            {
                "id": "head",
                "type": "Sphere",
                "params": { "radius": 0.1 },
                "transform": { "position": [0.0, 1.62, 0.0], "rotation": [0.0, 0.0, 0.0, 1.0], "scale": [0.95, 1.05, 1.0] },
                "material": { "baseColor": [0.5, 0.45, 0.4, 1.0], "metallic": 0.0, "roughness": 0.7 },
                "operation": "Union",
                "bone": "head"
            },
            {
                "id": "helmet",
                "type": "Sphere",
                "params": { "radius": 0.12 },
                "transform": { "position": [0.0, 1.68, 0.0], "rotation": [0.0, 0.0, 0.0, 1.0], "scale": [1.0, 1.1, 1.05] },
                "material": { "baseColor": [0.08, 0.08, 0.1, 1.0], "metallic": 0.9, "roughness": 0.3 },
                "operation": "SmoothUnion",
                "smoothness": 0.02,
                "bone": "head"
            },
            {
                "id": "helmet_crest",
                "type": "Cone",
                "params": { "radius": 0.06, "height": 0.2 },
                "transform": { "position": [0.0, 1.9, -0.02], "rotation": [-0.1, 0.0, 0.0, 0.995], "scale": [0.4, 1.0, 1.0] },
                "material": { "baseColor": [0.08, 0.08, 0.1, 1.0], "metallic": 0.9, "roughness": 0.3 },
                "operation": "Union",
                "bone": "head"
            },
            {
                "id": "helmet_horn_left",
                "type": "Cone",
                "params": { "radius": 0.025, "height": 0.15 },
                "transform": { "position": [-0.1, 1.78, 0.0], "rotation": [0.0, 0.0, 0.4, 0.92], "scale": [1.0, 1.0, 1.0] },
                "material": { "baseColor": [0.06, 0.06, 0.08, 1.0], "metallic": 0.85, "roughness": 0.35 },
                "operation": "Union",
                "bone": "head"
            },
            {
                "id": "helmet_horn_right",
                "type": "Cone",
                "params": { "radius": 0.025, "height": 0.15 },
                "transform": { "position": [0.1, 1.78, 0.0], "rotation": [0.0, 0.0, -0.4, 0.92], "scale": [1.0, 1.0, 1.0] },
                "material": { "baseColor": [0.06, 0.06, 0.08, 1.0], "metallic": 0.85, "roughness": 0.35 },
                "operation": "Union",
                "bone": "head"
            },
            {
                "id": "visor",
                "type": "RoundedBox",
                "params": { "size": [0.1, 0.03, 0.04], "radius": 0.01 },
                "transform": { "position": [0.0, 1.64, 0.1], "rotation": [0.0, 0.0, 0.0, 1.0], "scale": [1.0, 1.0, 1.0] },
                "material": { "baseColor": [0.02, 0.02, 0.02, 1.0], "metallic": 0.0, "roughness": 1.0 },
                "operation": "Union",
                "bone": "head"
            },
            {
                "id": "eye_glow_left",
                "type": "Sphere",
                "params": { "radius": 0.018 },
                "transform": { "position": [-0.03, 1.64, 0.1], "rotation": [0.0, 0.0, 0.0, 1.0], "scale": [1.0, 0.7, 0.4] },
                "material": { "baseColor": [0.3, 0.7, 1.0, 1.0], "metallic": 0.0, "roughness": 0.0, "emissive": [0.9, 2.1, 3.0] },
                "operation": "Union",
                "bone": "head"
            },
            {
                "id": "eye_glow_right",
                "type": "Sphere",
                "params": { "radius": 0.018 },
                "transform": { "position": [0.03, 1.64, 0.1], "rotation": [0.0, 0.0, 0.0, 1.0], "scale": [1.0, 0.7, 0.4] },
                "material": { "baseColor": [0.3, 0.7, 1.0, 1.0], "metallic": 0.0, "roughness": 0.0, "emissive": [0.9, 2.1, 3.0] },
                "operation": "Union",
                "bone": "head"
            },
            {
                "id": "shoulder_left",
                "type": "Sphere",
                "params": { "radius": 0.1 },
                "transform": { "position": [-0.22, 1.45, 0.0], "rotation": [0.0, 0.0, 0.0, 1.0], "scale": [1.3, 1.0, 1.1] },
                "material": { "baseColor": [0.08, 0.08, 0.1, 1.0], "metallic": 0.9, "roughness": 0.3 },
                "operation": "Union"
            },
            {
                "id": "shoulder_right",
                "type": "Sphere",
                "params": { "radius": 0.1 },
                "transform": { "position": [0.22, 1.45, 0.0], "rotation": [0.0, 0.0, 0.0, 1.0], "scale": [1.3, 1.0, 1.1] },
                "material": { "baseColor": [0.08, 0.08, 0.1, 1.0], "metallic": 0.9, "roughness": 0.3 },
                "operation": "Union"
            },
            {
                "id": "shoulder_spike_left",
                "type": "Cone",
                "params": { "radius": 0.03, "height": 0.12 },
                "transform": { "position": [-0.28, 1.52, 0.0], "rotation": [0.0, 0.0, 0.5, 0.87], "scale": [1.0, 1.0, 1.0] },
                "material": { "baseColor": [0.06, 0.06, 0.08, 1.0], "metallic": 0.9, "roughness": 0.25 },
                "operation": "Union"
            },
            {
                "id": "shoulder_spike_right",
                "type": "Cone",
                "params": { "radius": 0.03, "height": 0.12 },
                "transform": { "position": [0.28, 1.52, 0.0], "rotation": [0.0, 0.0, -0.5, 0.87], "scale": [1.0, 1.0, 1.0] },
                "material": { "baseColor": [0.06, 0.06, 0.08, 1.0], "metallic": 0.9, "roughness": 0.25 },
                "operation": "Union"
            },
            {
                "id": "shoulder_rune_left",
                "type": "Sphere",
                "params": { "radius": 0.025 },
                "transform": { "position": [-0.24, 1.47, 0.08], "rotation": [0.0, 0.0, 0.0, 1.0], "scale": [1.0, 1.0, 0.3] },
                "material": { "baseColor": [0.2, 0.5, 0.8, 1.0], "metallic": 0.0, "roughness": 0.0, "emissive": [0.1, 0.25, 0.4] },
                "operation": "Union"
            },
            {
                "id": "shoulder_rune_right",
                "type": "Sphere",
                "params": { "radius": 0.025 },
                "transform": { "position": [0.24, 1.47, 0.08], "rotation": [0.0, 0.0, 0.0, 1.0], "scale": [1.0, 1.0, 0.3] },
                "material": { "baseColor": [0.2, 0.5, 0.8, 1.0], "metallic": 0.0, "roughness": 0.0, "emissive": [0.1, 0.25, 0.4] },
                "operation": "Union"
            },
            {
                "id": "arm_left",
                "type": "Capsule",
                "params": { "radius": 0.045, "height": 0.38 },
                "transform": { "position": [-0.26, 1.12, 0.0], "rotation": [0.0, 0.0, 0.12, 0.99], "scale": [1.0, 1.0, 1.0] },
                "material": { "baseColor": [0.08, 0.08, 0.1, 1.0], "metallic": 0.85, "roughness": 0.35 },
                "operation": "Union",
                "bone": "arm_l"
            },
            {
                "id": "arm_right",
                "type": "Capsule",
                "params": { "radius": 0.045, "height": 0.38 },
                "transform": { "position": [0.26, 1.12, 0.0], "rotation": [0.0, 0.0, -0.12, 0.99], "scale": [1.0, 1.0, 1.0] },
                "material": { "baseColor": [0.08, 0.08, 0.1, 1.0], "metallic": 0.85, "roughness": 0.35 },
                "operation": "Union",
                "bone": "arm_r"
            },
            {
                "id": "gauntlet_left",
                "type": "RoundedBox",
                "params": { "size": [0.04, 0.08, 0.05], "radius": 0.015 },
                "transform": { "position": [-0.3, 0.88, 0.0], "rotation": [0.0, 0.0, 0.0, 1.0], "scale": [1.0, 1.0, 1.0] },
                "material": { "baseColor": [0.08, 0.08, 0.1, 1.0], "metallic": 0.9, "roughness": 0.3 },
                "operation": "Union",
                "bone": "arm_l"
            },
            {
                "id": "gauntlet_right",
                "type": "RoundedBox",
                "params": { "size": [0.04, 0.08, 0.05], "radius": 0.015 },
                "transform": { "position": [0.3, 0.88, 0.0], "rotation": [0.0, 0.0, 0.0, 1.0], "scale": [1.0, 1.0, 1.0] },
                "material": { "baseColor": [0.08, 0.08, 0.1, 1.0], "metallic": 0.9, "roughness": 0.3 },
                "operation": "Union",
                "bone": "arm_r"
            },
            {
                "id": "leg_left",
                "type": "Capsule",
                "params": { "radius": 0.055, "height": 0.48 },
                "transform": { "position": [-0.08, 0.48, 0.0], "rotation": [0.0, 0.0, 0.0, 1.0], "scale": [1.0, 1.0, 0.9] },
                "material": { "baseColor": [0.08, 0.08, 0.1, 1.0], "metallic": 0.85, "roughness": 0.35 },
                "operation": "Union",
                "bone": "leg_l"
            },
            {
                "id": "leg_right",
                "type": "Capsule",
                "params": { "radius": 0.055, "height": 0.48 },
                "transform": { "position": [0.08, 0.48, 0.0], "rotation": [0.0, 0.0, 0.0, 1.0], "scale": [1.0, 1.0, 0.9] },
                "material": { "baseColor": [0.08, 0.08, 0.1, 1.0], "metallic": 0.85, "roughness": 0.35 },
                "operation": "Union",
                "bone": "leg_r"
            },
            {
                "id": "boot_left",
                "type": "RoundedBox",
                "params": { "size": [0.055, 0.08, 0.12], "radius": 0.02 },
                "transform": { "position": [-0.08, 0.04, 0.02], "rotation": [0.0, 0.0, 0.0, 1.0], "scale": [1.0, 1.0, 1.0] },
                "material": { "baseColor": [0.06, 0.06, 0.08, 1.0], "metallic": 0.85, "roughness": 0.4 },
                "operation": "Union",
                "bone": "leg_l"
            },
            {
                "id": "boot_right",
                "type": "RoundedBox",
                "params": { "size": [0.055, 0.08, 0.12], "radius": 0.02 },
                "transform": { "position": [0.08, 0.04, 0.02], "rotation": [0.0, 0.0, 0.0, 1.0], "scale": [1.0, 1.0, 1.0] },
                "material": { "baseColor": [0.06, 0.06, 0.08, 1.0], "metallic": 0.85, "roughness": 0.4 },
                "operation": "Union",
                "bone": "leg_r"
            },
            {
                "id": "runeblade_blade",
                "type": "RoundedBox",
                "params": { "size": [0.04, 0.65, 0.012], "radius": 0.005 },
                "transform": { "position": [0.38, 1.2, 0.0], "rotation": [0.0, 0.0, 0.0, 1.0], "scale": [1.0, 1.0, 1.0] },
                "material": { "baseColor": [0.15, 0.15, 0.2, 1.0], "metallic": 0.95, "roughness": 0.15 },
                "operation": "Union",
                "bone": "arm_r"
            },
            {
                "id": "runeblade_rune_1",
                "type": "Capsule",
                "params": { "radius": 0.008, "height": 0.12 },
                "transform": { "position": [0.38, 1.3, 0.015], "rotation": [0.0, 0.0, 0.0, 1.0], "scale": [1.0, 1.0, 0.3] },
                "material": { "baseColor": [0.2, 0.6, 1.0, 1.0], "metallic": 0.0, "roughness": 0.0, "emissive": [0.2, 0.6, 1.0] },
                "operation": "Union",
                "bone": "arm_r"
            },
            {
                "id": "runeblade_rune_2",
                "type": "Capsule",
                "params": { "radius": 0.008, "height": 0.1 },
                "transform": { "position": [0.38, 1.1, 0.015], "rotation": [0.0, 0.0, 0.0, 1.0], "scale": [1.0, 1.0, 0.3] },
                "material": { "baseColor": [0.2, 0.6, 1.0, 1.0], "metallic": 0.0, "roughness": 0.0, "emissive": [0.2, 0.6, 1.0] },
                "operation": "Union",
                "bone": "arm_r"
            },
            {
                "id": "runeblade_hilt",
                "type": "Cylinder",
                "params": { "radius": 0.02, "height": 0.15 },
                "transform": { "position": [0.38, 0.8, 0.0], "rotation": [0.0, 0.0, 0.0, 1.0], "scale": [1.0, 1.0, 1.0] },
                "material": { "baseColor": [0.1, 0.08, 0.05, 1.0], "metallic": 0.5, "roughness": 0.6 },
                "operation": "Union",
                "bone": "arm_r"
            },
            {
                "id": "runeblade_guard",
                "type": "RoundedBox",
                "params": { "size": [0.1, 0.025, 0.025], "radius": 0.008 },
                "transform": { "position": [0.38, 0.87, 0.0], "rotation": [0.0, 0.0, 0.0, 1.0], "scale": [1.0, 1.0, 1.0] },
                "material": { "baseColor": [0.08, 0.08, 0.1, 1.0], "metallic": 0.9, "roughness": 0.25 },
                "operation": "Union",
                "bone": "arm_r"
            },
            {
                "id": "runeblade_pommel",
                "type": "Sphere",
                "params": { "radius": 0.025 },
                "transform": { "position": [0.38, 0.72, 0.0], "rotation": [0.0, 0.0, 0.0, 1.0], "scale": [1.0, 1.0, 1.0] },
                "material": { "baseColor": [0.2, 0.5, 0.8, 1.0], "metallic": 0.0, "roughness": 0.0, "emissive": [0.15, 0.38, 0.6] },
                "operation": "Union",
                "bone": "arm_r"
            },
            {
                "id": "cloak",
                "type": "Cone",
                "params": { "radius": 0.35, "height": 1.0 },
                "transform": { "position": [0.0, 0.8, -0.1], "rotation": [0.0, 0.0, 0.0, 1.0], "scale": [1.0, 1.0, 0.4] },
                "material": { "baseColor": [0.05, 0.05, 0.08, 1.0], "metallic": 0.0, "roughness": 0.9 },
                "operation": "Union"
            },
            {
                "id": "unholy_aura",
                "type": "Sphere",
                "params": { "radius": 0.6 },
                "transform": { "position": [0.0, 1.1, 0.0], "rotation": [0.0, 0.0, 0.0, 1.0], "scale": [1.0, 1.2, 1.0] },
                "material": { "baseColor": [0.2, 0.5, 0.8, 0.1], "metallic": 0.0, "roughness": 0.0, "emissive": [0.02, 0.05, 0.08] },
                "operation": "Union"
            }
        ]
    },

    "skeleton": {
        "bones": [
            { "name": "root", "parent": null, "position": [0.0, 0.0, 0.0], "rotation": [0.0, 0.0, 0.0, 1.0] },
            { "name": "spine", "parent": "root", "position": [0.0, 0.9, 0.0], "rotation": [0.0, 0.0, 0.0, 1.0] },
            { "name": "chest", "parent": "spine", "position": [0.0, 0.3, 0.0], "rotation": [0.0, 0.0, 0.0, 1.0] },
            { "name": "head", "parent": "chest", "position": [0.0, 0.4, 0.0], "rotation": [0.0, 0.0, 0.0, 1.0] },
            { "name": "arm_l", "parent": "chest", "position": [-0.18, 0.22, 0.0], "rotation": [0.0, 0.0, 0.1, 0.995] },
            { "name": "arm_r", "parent": "chest", "position": [0.18, 0.22, 0.0], "rotation": [0.0, 0.0, -0.1, 0.995] },
            { "name": "leg_l", "parent": "root", "position": [-0.08, 0.75, 0.0], "rotation": [0.0, 0.0, 0.0, 1.0] },
            { "name": "leg_r", "parent": "root", "position": [0.08, 0.75, 0.0], "rotation": [0.0, 0.0, 0.0, 1.0] }
        ]
    },

    "animations": {
        "idle": {
            "duration": 2.5, "loop": true,
            "keyframes": [
                { "time": 0.0, "bones": { "spine": { "rotation": [0.0, 0.0, 0.0, 1.0] }, "head": { "rotation": [0.0, 0.0, 0.0, 1.0] }, "arm_l": { "rotation": [0.0, 0.0, 0.1, 0.995] }, "arm_r": { "rotation": [0.0, 0.0, -0.1, 0.995] } } },
                { "time": 0.6, "bones": { "spine": { "rotation": [0.02, 0.0, 0.0, 0.9998] }, "head": { "rotation": [0.0, 0.05, 0.0, 0.999] }, "arm_l": { "rotation": [0.02, 0.0, 0.12, 0.99] }, "arm_r": { "rotation": [-0.02, 0.0, -0.08, 0.997] } } },
                { "time": 1.25, "bones": { "spine": { "rotation": [0.0, 0.0, 0.0, 1.0] }, "head": { "rotation": [0.02, -0.03, 0.0, 0.999] }, "arm_l": { "rotation": [-0.01, 0.0, 0.08, 0.997] }, "arm_r": { "rotation": [0.01, 0.0, -0.12, 0.99] } } },
                { "time": 1.9, "bones": { "spine": { "rotation": [0.01, 0.0, 0.0, 0.9999] }, "head": { "rotation": [-0.01, 0.02, 0.0, 0.9998] }, "arm_l": { "rotation": [0.01, 0.0, 0.11, 0.994] }, "arm_r": { "rotation": [-0.01, 0.0, -0.09, 0.996] } } },
                { "time": 2.5, "bones": { "spine": { "rotation": [0.0, 0.0, 0.0, 1.0] }, "head": { "rotation": [0.0, 0.0, 0.0, 1.0] }, "arm_l": { "rotation": [0.0, 0.0, 0.1, 0.995] }, "arm_r": { "rotation": [0.0, 0.0, -0.1, 0.995] } } }
            ]
        },
        "walk": {
            "duration": 0.85, "loop": true,
            "keyframes": [
                { "time": 0.0, "bones": { "root": { "position": [0.0, 0.0, 0.0] }, "leg_l": { "rotation": [0.28, 0.0, 0.0, 0.96] }, "leg_r": { "rotation": [-0.28, 0.0, 0.0, 0.96] }, "arm_l": { "rotation": [0.1, 0.0, 0.1, 0.99] }, "arm_r": { "rotation": [-0.15, 0.0, -0.1, 0.98] } } },
                { "time": 0.425, "bones": { "root": { "position": [0.0, 0.03, 0.0] }, "leg_l": { "rotation": [-0.28, 0.0, 0.0, 0.96] }, "leg_r": { "rotation": [0.28, 0.0, 0.0, 0.96] }, "arm_l": { "rotation": [-0.1, 0.0, 0.1, 0.99] }, "arm_r": { "rotation": [0.15, 0.0, -0.1, 0.98] } } },
                { "time": 0.85, "bones": { "root": { "position": [0.0, 0.0, 0.0] }, "leg_l": { "rotation": [0.28, 0.0, 0.0, 0.96] }, "leg_r": { "rotation": [-0.28, 0.0, 0.0, 0.96] }, "arm_l": { "rotation": [0.1, 0.0, 0.1, 0.99] }, "arm_r": { "rotation": [-0.15, 0.0, -0.1, 0.98] } } }
            ]
        },
        "attack": {
            "duration": 1.0, "loop": false,
            "keyframes": [
                { "time": 0.0, "bones": { "chest": { "rotation": [0.0, -0.15, 0.0, 0.99] }, "arm_r": { "rotation": [-0.3, 0.0, -0.45, 0.84] } } },
                { "time": 0.3, "bones": { "chest": { "rotation": [0.0, -0.3, 0.0, 0.95] }, "arm_r": { "rotation": [-0.5, 0.0, -0.55, 0.67] } } },
                { "time": 0.5, "bones": { "chest": { "rotation": [0.0, 0.25, 0.0, 0.97] }, "arm_r": { "rotation": [0.35, 0.0, -0.55, 0.76] } }, "events": ["runeblade_hit"] },
                { "time": 0.75, "bones": { "chest": { "rotation": [0.0, 0.15, 0.0, 0.99] }, "arm_r": { "rotation": [0.15, 0.0, -0.3, 0.94] } } },
                { "time": 1.0, "bones": { "chest": { "rotation": [0.0, 0.0, 0.0, 1.0] }, "arm_r": { "rotation": [0.0, 0.0, -0.1, 0.995] } } }
            ]
        },
        "cast": {
            "duration": 1.2, "loop": false,
            "keyframes": [
                { "time": 0.0, "bones": { "spine": { "rotation": [0.0, 0.0, 0.0, 1.0] }, "arm_l": { "rotation": [0.0, 0.0, 0.1, 0.995] } } },
                { "time": 0.3, "bones": { "spine": { "rotation": [-0.1, 0.0, 0.0, 0.995] }, "arm_l": { "rotation": [-0.4, 0.2, 0.5, 0.74] } } },
                { "time": 0.6, "bones": { "spine": { "rotation": [-0.15, 0.0, 0.0, 0.99] }, "arm_l": { "rotation": [-0.5, 0.3, 0.6, 0.55] } }, "events": ["spell_release"] },
                { "time": 0.9, "bones": { "spine": { "rotation": [-0.05, 0.0, 0.0, 0.999] }, "arm_l": { "rotation": [-0.2, 0.1, 0.3, 0.93] } } },
                { "time": 1.2, "bones": { "spine": { "rotation": [0.0, 0.0, 0.0, 1.0] }, "arm_l": { "rotation": [0.0, 0.0, 0.1, 0.995] } } }
            ]
        },
        "death": {
            "duration": 2.0, "loop": false,
            "keyframes": [
                { "time": 0.0, "bones": { "root": { "position": [0.0, 0.0, 0.0], "rotation": [0.0, 0.0, 0.0, 1.0] } } },
                { "time": 0.5, "bones": { "root": { "position": [0.0, -0.15, 0.08], "rotation": [0.15, 0.0, 0.12, 0.98] } } },
                { "time": 1.0, "bones": { "root": { "position": [0.0, -0.4, 0.2], "rotation": [0.35, 0.0, 0.2, 0.91] } } },
                { "time": 2.0, "bones": { "root": { "position": [0.0, -0.85, 0.35], "rotation": [0.6, 0.0, 0.15, 0.79] } } }
            ]
        }
    },

    "animationStateMachine": {
        "initialState": "idle",
        "states": {
            "idle": { "animation": "idle", "transitions": [{ "to": "walk", "condition": "isMoving" }, { "to": "attack", "condition": "isAttacking" }, { "to": "cast", "condition": "isCasting" }, { "to": "death", "condition": "isDead" }] },
            "walk": { "animation": "walk", "transitions": [{ "to": "idle", "condition": "!isMoving" }, { "to": "attack", "condition": "isAttacking" }, { "to": "cast", "condition": "isCasting" }, { "to": "death", "condition": "isDead" }] },
            "attack": { "animation": "attack", "transitions": [{ "to": "idle", "condition": "animationComplete && !isMoving" }, { "to": "walk", "condition": "animationComplete && isMoving" }, { "to": "death", "condition": "isDead" }] },
            "cast": { "animation": "cast", "transitions": [{ "to": "idle", "condition": "animationComplete && !isMoving" }, { "to": "walk", "condition": "animationComplete && isMoving" }, { "to": "death", "condition": "isDead" }] },
            "death": { "animation": "death", "transitions": [] }
        }
    },

    "abilities": [
        { "id": "death_coil", "name": "Death Coil", "description": "Fires a bolt of death energy that damages enemies or heals undead units.", "hotkey": "C", "isToggle": false, "manaCost": 75, "damage": 100, "healing": 200, "cooldown": 6.0, "range": 800, "level": 1 },
        { "id": "death_pact", "name": "Death Pact", "description": "Sacrifices a friendly undead unit to restore health.", "hotkey": "E", "isToggle": false, "manaCost": 50, "healthPercent": 2.0, "cooldown": 8.0, "range": 700, "level": 1 },
        { "id": "unholy_aura", "name": "Unholy Aura", "description": "Increases movement speed and life regeneration of nearby friendly units.", "hotkey": "U", "isToggle": false, "isPassive": true, "moveSpeedBonus": 0.1, "healthRegen": 1.0, "radius": 900, "level": 1 },
        { "id": "animate_dead", "name": "Animate Dead", "description": "Raises nearby corpses as invulnerable undead servants for a short time.", "hotkey": "D", "isToggle": false, "manaCost": 175, "duration": 40.0, "corpseCount": 6, "cooldown": 240.0, "level": 6, "isUltimate": true }
    ],

    "behaviors": {
        "on_spawn": { "actions": [{ "type": "play_sound", "sound": "death_knight_ready" }, { "type": "random_say", "texts": ["I was once a paladin.", "Let darkness consume you.", "Death awaits all."], "chance": 1.0 }, { "type": "spawn_particles", "effect": "unholy_mist" }] },
        "on_attack": { "actions": [{ "type": "play_animation", "animation": "attack" }, { "type": "play_sound", "sound": "runeblade_swing" }] },
        "on_cast": { "actions": [{ "type": "play_animation", "animation": "cast" }, { "type": "play_sound", "sound": "death_magic" }, { "type": "spawn_particles", "effect": "death_energy" }] },
        "on_death": { "actions": [{ "type": "play_animation", "animation": "death" }, { "type": "play_sound", "sound": "death_knight_death" }, { "type": "spawn_particles", "effect": "unholy_explosion" }] }
    }
}
