{
    "id": "meat_wagon",
    "name": "Meat Wagon",
    "race": "undead",
    "type": "unit",
    "category": "siege",
    "description": "Gruesome siege engine that hurls diseased corpses at enemy buildings. Collects and transports corpses for necromancers.",
    "stats": {
        "health": 380,
        "armor": 2,
        "damage": 60,
        "attackSpeed": 3.0,
        "moveSpeed": 200,
        "attackRange": 1000,
        "splashRadius": 150,
        "bonusVsBuildings": 2.0
    },
    "costs": {
        "gold": 230,
        "lumber": 50,
        "food": 4,
        "buildTime": 35.0
    },
    "sdfModel": {
        "name": "Meat Wagon",
        "bounds": {
            "min": [
                -1.0,
                0.0,
                -1.0
            ],
            "max": [
                1.0,
                1.5,
                1.0
            ]
        },
        "primitives": [
            {
                "id": "chassis_base",
                "type": "RoundedBox",
                "params": {
                    "size": [
                        0.8,
                        0.2,
                        1.4
                    ],
                    "radius": 0.05
                },
                "transform": {
                    "position": [
                        0.0,
                        0.4,
                        0.0
                    ],
                    "rotation": [
                        0.0,
                        0.0,
                        0.0,
                        1.0
                    ],
                    "scale": [
                        1.0,
                        1.0,
                        1.0
                    ]
                },
                "material": {
                    "baseColor": [
                        0.2,
                        0.15,
                        0.1,
                        1.0
                    ],
                    "metallic": 0.2,
                    "roughness": 0.8
                },
                "operation": "Union"
            },
            {
                "id": "chassis_rivet_1",
                "type": "Sphere",
                "params": {
                    "radius": 0.03
                },
                "transform": {
                    "position": [
                        0.4,
                        0.5,
                        0.6
                    ],
                    "rotation": [
                        0.0,
                        0.0,
                        0.0,
                        1.0
                    ],
                    "scale": [
                        1.0,
                        1.0,
                        1.0
                    ]
                },
                "material": {
                    "baseColor": [
                        0.4,
                        0.3,
                        0.2,
                        1.0
                    ],
                    "metallic": 0.8,
                    "roughness": 0.3
                },
                "operation": "Union"
            },
            {
                "id": "chassis_rivet_2",
                "type": "Sphere",
                "params": {
                    "radius": 0.03
                },
                "transform": {
                    "position": [
                        -0.4,
                        0.5,
                        0.6
                    ],
                    "rotation": [
                        0.0,
                        0.0,
                        0.0,
                        1.0
                    ],
                    "scale": [
                        1.0,
                        1.0,
                        1.0
                    ]
                },
                "material": {
                    "baseColor": [
                        0.4,
                        0.3,
                        0.2,
                        1.0
                    ],
                    "metallic": 0.8,
                    "roughness": 0.3
                },
                "operation": "Union"
            },
            {
                "id": "meat_container",
                "type": "RoundedBox",
                "params": {
                    "size": [
                        0.7,
                        0.4,
                        0.8
                    ],
                    "radius": 0.03
                },
                "transform": {
                    "position": [
                        0.0,
                        0.7,
                        -0.2
                    ],
                    "rotation": [
                        0.0,
                        0.0,
                        0.0,
                        1.0
                    ],
                    "scale": [
                        1.0,
                        1.0,
                        1.0
                    ]
                },
                "material": {
                    "baseColor": [
                        0.3,
                        0.25,
                        0.18,
                        1.0
                    ],
                    "metallic": 0.1,
                    "roughness": 0.85
                },
                "operation": "Union"
            },
            {
                "id": "meat_pile",
                "type": "Ellipsoid",
                "params": {
                    "radii": [
                        0.3,
                        0.2,
                        0.35
                    ]
                },
                "transform": {
                    "position": [
                        0.0,
                        0.95,
                        -0.2
                    ],
                    "rotation": [
                        0.0,
                        0.0,
                        0.0,
                        1.0
                    ],
                    "scale": [
                        1.0,
                        1.0,
                        1.0
                    ]
                },
                "material": {
                    "baseColor": [
                        0.5,
                        0.2,
                        0.18,
                        1.0
                    ],
                    "metallic": 0.0,
                    "roughness": 0.7,
                    "subsurface": 0.4
                },
                "operation": "Union"
            },
            {
                "id": "corpse_arm_1",
                "type": "Capsule",
                "params": {
                    "radius": 0.03,
                    "height": 0.2
                },
                "transform": {
                    "position": [
                        -0.2,
                        1.0,
                        -0.15
                    ],
                    "rotation": [
                        0.3,
                        0.5,
                        0.2,
                        0.79
                    ],
                    "scale": [
                        1.0,
                        1.0,
                        1.0
                    ]
                },
                "material": {
                    "baseColor": [
                        0.5,
                        0.45,
                        0.35,
                        1.0
                    ],
                    "metallic": 0.0,
                    "roughness": 0.8,
                    "subsurface": 0.5
                },
                "operation": "Union"
            },
            {
                "id": "corpse_leg_1",
                "type": "Capsule",
                "params": {
                    "radius": 0.035,
                    "height": 0.25
                },
                "transform": {
                    "position": [
                        0.15,
                        1.05,
                        -0.35
                    ],
                    "rotation": [
                        -0.2,
                        0.3,
                        -0.4,
                        0.84
                    ],
                    "scale": [
                        1.0,
                        1.0,
                        1.0
                    ]
                },
                "material": {
                    "baseColor": [
                        0.45,
                        0.4,
                        0.3,
                        1.0
                    ],
                    "metallic": 0.0,
                    "roughness": 0.8,
                    "subsurface": 0.5
                },
                "operation": "Union"
            },
            {
                "id": "wheel_1",
                "type": "Cylinder",
                "params": {
                    "radius": 0.2,
                    "height": 0.1
                },
                "transform": {
                    "position": [
                        0.5,
                        0.2,
                        0.7
                    ],
                    "rotation": [
                        0.0,
                        0.0,
                        0.707,
                        0.707
                    ],
                    "scale": [
                        1.0,
                        1.0,
                        1.0
                    ]
                },
                "material": {
                    "baseColor": [
                        0.1,
                        0.1,
                        0.1,
                        1.0
                    ],
                    "metallic": 0.9,
                    "roughness": 0.2,
                    "anisotropy": 0.5,
                    "anisotropyRotation": 45
                },
                "operation": "Union"
            },
            {
                "id": "wheel_2",
                "type": "Cylinder",
                "params": {
                    "radius": 0.2,
                    "height": 0.1
                },
                "transform": {
                    "position": [
                        -0.5,
                        0.2,
                        0.7
                    ],
                    "rotation": [
                        0.0,
                        0.0,
                        0.707,
                        0.707
                    ],
                    "scale": [
                        1.0,
                        1.0,
                        1.0
                    ]
                },
                "material": {
                    "baseColor": [
                        0.1,
                        0.1,
                        0.1,
                        1.0
                    ],
                    "metallic": 0.9,
                    "roughness": 0.2,
                    "anisotropy": 0.5,
                    "anisotropyRotation": 45
                },
                "operation": "Union"
            },
            {
                "id": "handle_base",
                "type": "Cylinder",
                "params": {
                    "radius": 0.04,
                    "height": 0.7
                },
                "transform": {
                    "position": [
                        0.0,
                        0.8,
                        0.7
                    ],
                    "rotation": [
                        0.707,
                        0.0,
                        0.0,
                        0.707
                    ],
                    "scale": [
                        1.0,
                        1.0,
                        1.0
                    ]
                },
                "material": {
                    "baseColor": [
                        0.2,
                        0.15,
                        0.1,
                        1.0
                    ],
                    "metallic": 0.7,
                    "roughness": 0.4
                },
                "operation": "Union"
            },
            {
                "id": "handle_grip_1",
                "type": "Cylinder",
                "params": {
                    "radius": 0.05,
                    "height": 0.2
                },
                "transform": {
                    "position": [
                        0.0,
                        1.3,
                        0.7
                    ],
                    "rotation": [
                        0.707,
                        0.0,
                        0.0,
                        0.707
                    ],
                    "scale": [
                        1.0,
                        1.0,
                        1.0
                    ]
                },
                "material": {
                    "baseColor": [
                        0.1,
                        0.08,
                        0.06,
                        1.0
                    ],
                    "metallic": 0.1,
                    "roughness": 0.9
                },
                "operation": "Union"
            },
            {
                "id": "handle_grip_2",
                "type": "Cylinder",
                "params": {
                    "radius": 0.05,
                    "height": 0.2
                },
                "transform": {
                    "position": [
                        0.0,
                        0.3,
                        0.7
                    ],
                    "rotation": [
                        0.707,
                        0.0,
                        0.0,
                        0.707
                    ],
                    "scale": [
                        1.0,
                        1.0,
                        1.0
                    ]
                },
                "material": {
                    "baseColor": [
                        0.1,
                        0.08,
                        0.06,
                        1.0
                    ],
                    "metallic": 0.1,
                    "roughness": 0.9
                },
                "operation": "Union"
            },
            {
                "id": "cage_support_1",
                "type": "Cylinder",
                "params": {
                    "radius": 0.02,
                    "height": 0.9
                },
                "transform": {
                    "position": [
                        0.35,
                        0.9,
                        0.2
                    ],
                    "rotation": [
                        0.0,
                        0.0,
                        0.0,
                        1.0
                    ],
                    "scale": [
                        1.0,
                        1.0,
                        1.0
                    ]
                },
                "material": {
                    "baseColor": [
                        0.25,
                        0.2,
                        0.15,
                        1.0
                    ],
                    "metallic": 0.7,
                    "roughness": 0.5
                },
                "operation": "Union"
            },
            {
                "id": "cage_support_2",
                "type": "Cylinder",
                "params": {
                    "radius": 0.02,
                    "height": 0.9
                },
                "transform": {
                    "position": [
                        -0.35,
                        0.9,
                        0.2
                    ],
                    "rotation": [
                        0.0,
                        0.0,
                        0.0,
                        1.0
                    ],
                    "scale": [
                        1.0,
                        1.0,
                        1.0
                    ]
                },
                "material": {
                    "baseColor": [
                        0.25,
                        0.2,
                        0.15,
                        1.0
                    ],
                    "metallic": 0.7,
                    "roughness": 0.5
                },
                "operation": "Union"
            },
            {
                "id": "cage_top",
                "type": "Cylinder",
                "params": {
                    "radius": 0.7,
                    "height": 0.02
                },
                "transform": {
                    "position": [
                        0.0,
                        1.3,
                        -0.2
                    ],
                    "rotation": [
                        0.0,
                        0.0,
                        0.0,
                        1.0
                    ],
                    "scale": [
                        1.0,
                        1.0,
                        1.0
                    ]
                },
                "material": {
                    "baseColor": [
                        0.25,
                        0.2,
                        0.15,
                        1.0
                    ],
                    "metallic": 0.7,
                    "roughness": 0.5
                },
                "operation": "Union"
            },
            {
                "id": "cage_bottom",
                "type": "Cylinder",
                "params": {
                    "radius": 0.7,
                    "height": 0.02
                },
                "transform": {
                    "position": [
                        0.0,
                        0.5,
                        -0.2
                    ],
                    "rotation": [
                        0.0,
                        0.0,
                        0.0,
                        1.0
                    ],
                    "scale": [
                        1.0,
                        1.0,
                        1.0
                    ]
                },
                "material": {
                    "baseColor": [
                        0.25,
                        0.2,
                        0.15,
                        1.0
                    ],
                    "metallic": 0.7,
                    "roughness": 0.5
                },
                "operation": "Union"
            },
            {
                "id": "meat_container_straps_1",
                "type": "RoundedBox",
                "params": {
                    "size": [
                        0.1,
                        0.05,
                        0.8
                    ],
                    "radius": 0.01
                },
                "transform": {
                    "position": [
                        0.35,
                        0.7,
                        -0.2
                    ],
                    "rotation": [
                        0.0,
                        0.0,
                        0.0,
                        1.0
                    ],
                    "scale": [
                        1.0,
                        1.0,
                        1.0
                    ]
                },
                "material": {
                    "baseColor": [
                        0.15,
                        0.1,
                        0.05,
                        1.0
                    ],
                    "metallic": 0.05,
                    "roughness": 0.9
                },
                "operation": "Union"
            },
            {
                "id": "meat_container_straps_2",
                "type": "RoundedBox",
                "params": {
                    "size": [
                        0.1,
                        0.05,
                        0.8
                    ],
                    "radius": 0.01
                },
                "transform": {
                    "position": [
                        -0.35,
                        0.7,
                        -0.2
                    ],
                    "rotation": [
                        0.0,
                        0.0,
                        0.0,
                        1.0
                    ],
                    "scale": [
                        1.0,
                        1.0,
                        1.0
                    ]
                },
                "material": {
                    "baseColor": [
                        0.15,
                        0.1,
                        0.05,
                        1.0
                    ],
                    "metallic": 0.05,
                    "roughness": 0.9
                },
                "operation": "Union"
            },
            {
                "id": "meat_container_stitches_1",
                "type": "Cylinder",
                "params": {
                    "radius": 0.01,
                    "height": 0.7
                },
                "transform": {
                    "position": [
                        0.0,
                        0.7,
                        0.2
                    ],
                    "rotation": [
                        0.0,
                        0.0,
                        0.707,
                        0.707
                    ],
                    "scale": [
                        1.0,
                        1.0,
                        1.0
                    ]
                },
                "material": {
                    "baseColor": [
                        0.8,
                        0.7,
                        0.6,
                        1.0
                    ],
                    "metallic": 0.1,
                    "roughness": 0.7
                },
                "operation": "Union"
            },
            {
                "id": "meat_container_scar_1",
                "type": "Capsule",
                "params": {
                    "radius": 0.02,
                    "height": 0.2
                },
                "transform": {
                    "position": [
                        0.2,
                        0.8,
                        -0.6
                    ],
                    "rotation": [
                        0.0,
                        0.2,
                        0.0,
                        0.98
                    ],
                    "scale": [
                        1.0,
                        1.0,
                        1.0
                    ]
                },
                "material": {
                    "baseColor": [
                        0.7,
                        0.6,
                        0.5,
                        1.0
                    ],
                    "metallic": 0.0,
                    "roughness": 0.8,
                    "subsurface": 0.3
                },
                "operation": "Union"
            },
            {
                "id": "wear_mark_1",
                "type": "Sphere",
                "params": {
                    "radius": 0.1
                },
                "transform": {
                    "position": [
                        0.4,
                        0.4,
                        0.4
                    ],
                    "rotation": [
                        0.0,
                        0.0,
                        0.0,
                        1.0
                    ],
                    "scale": [
                        1.0,
                        1.0,
                        1.0
                    ]
                },
                "material": {
                    "baseColor": [
                        0.1,
                        0.05,
                        0.02,
                        1.0
                    ],
                    "metallic": 0.0,
                    "roughness": 0.9
                },
                "operation": "Subtraction"
            },
            {
                "id": "wear_mark_2",
                "type": "Sphere",
                "params": {
                    "radius": 0.08
                },
                "transform": {
                    "position": [
                        -0.4,
                        0.4,
                        0.4
                    ],
                    "rotation": [
                        0.0,
                        0.0,
                        0.0,
                        1.0
                    ],
                    "scale": [
                        1.0,
                        1.0,
                        1.0
                    ]
                },
                "material": {
                    "baseColor": [
                        0.1,
                        0.05,
                        0.02,
                        1.0
                    ],
                    "metallic": 0.0,
                    "roughness": 0.9
                },
                "operation": "Subtraction"
            },
            {
                "id": "magic_rune_1",
                "type": "Torus",
                "params": {
                    "radius": 0.04,
                    "thickness": 0.01
                },
                "transform": {
                    "position": [
                        0.0,
                        0.6,
                        0.7
                    ],
                    "rotation": [
                        0.707,
                        0.0,
                        0.0,
                        0.707
                    ],
                    "scale": [
                        1.0,
                        1.0,
                        1.0
                    ]
                },
                "material": {
                    "baseColor": [
                        0.9,
                        0.8,
                        0.0,
                        1.0
                    ],
                    "metallic": 1.0,
                    "roughness": 0.2,
                    "emissive": [
                        1.0,
                        0.8,
                        0.0
                    ]
                },
                "operation": "Union"
            },
            {
                "id": "corpse_head_1",
                "type": "Sphere",
                "params": {
                    "radius": 0.07
                },
                "transform": {
                    "position": [
                        -0.1,
                        1.15,
                        -0.3
                    ],
                    "rotation": [
                        0.0,
                        0.0,
                        0.0,
                        1.0
                    ],
                    "scale": [
                        1.0,
                        1.0,
                        1.0
                    ]
                },
                "material": {
                    "baseColor": [
                        0.5,
                        0.45,
                        0.35,
                        1.0
                    ],
                    "metallic": 0.0,
                    "roughness": 0.8,
                    "subsurface": 0.5
                },
                "operation": "Union"
            },
            {
                "id": "corpse_arm_2",
                "type": "Capsule",
                "params": {
                    "radius": 0.03,
                    "height": 0.2
                },
                "transform": {
                    "position": [
                        0.2,
                        1.0,
                        -0.15
                    ],
                    "rotation": [
                        -0.3,
                        0.5,
                        -0.2,
                        0.79
                    ],
                    "scale": [
                        1.0,
                        1.0,
                        1.0
                    ]
                },
                "material": {
                    "baseColor": [
                        0.5,
                        0.45,
                        0.35,
                        1.0
                    ],
                    "metallic": 0.0,
                    "roughness": 0.8,
                    "subsurface": 0.5
                },
                "operation": "Union"
            }
        ]
    },
    "skeleton": {
        "bones": [
            {
                "name": "root",
                "parent": null,
                "position": [
                    0.0,
                    0.0,
                    0.0
                ],
                "rotation": [
                    0.0,
                    0.0,
                    0.0,
                    1.0
                ]
            },
            {
                "name": "chassis",
                "parent": "root",
                "position": [
                    0.0,
                    0.4,
                    0.0
                ],
                "rotation": [
                    0.0,
                    0.0,
                    0.0,
                    1.0
                ]
            },
            {
                "name": "catapult_arm",
                "parent": "chassis",
                "position": [
                    0.0,
                    0.5,
                    0.4
                ],
                "rotation": [
                    -0.35,
                    0.0,
                    0.0,
                    0.94
                ]
            },
            {
                "name": "wheel_lf",
                "parent": "chassis",
                "position": [
                    -0.5,
                    -0.15,
                    0.5
                ],
                "rotation": [
                    0.0,
                    0.0,
                    0.0,
                    1.0
                ]
            },
            {
                "name": "wheel_rf",
                "parent": "chassis",
                "position": [
                    0.5,
                    -0.15,
                    0.5
                ],
                "rotation": [
                    0.0,
                    0.0,
                    0.0,
                    1.0
                ]
            },
            {
                "name": "wheel_lb",
                "parent": "chassis",
                "position": [
                    -0.52,
                    -0.1,
                    -0.5
                ],
                "rotation": [
                    0.0,
                    0.0,
                    0.0,
                    1.0
                ]
            },
            {
                "name": "wheel_rb",
                "parent": "chassis",
                "position": [
                    0.52,
                    -0.1,
                    -0.5
                ],
                "rotation": [
                    0.0,
                    0.0,
                    0.0,
                    1.0
                ]
            }
        ]
    },
    "animations": {
        "idle": {
            "duration": 2.0,
            "loop": true,
            "keyframes": [
                {
                    "time": 0.0,
                    "bones": {
                        "chassis": {
                            "position": [
                                0.0,
                                0.4,
                                0.0
                            ]
                        },
                        "catapult_arm": {
                            "rotation": [
                                -0.35,
                                0.0,
                                0.0,
                                0.94
                            ]
                        }
                    }
                },
                {
                    "time": 1.0,
                    "bones": {
                        "chassis": {
                            "position": [
                                0.0,
                                0.42,
                                0.0
                            ]
                        },
                        "catapult_arm": {
                            "rotation": [
                                -0.36,
                                0.0,
                                0.0,
                                0.93
                            ]
                        }
                    }
                },
                {
                    "time": 2.0,
                    "bones": {
                        "chassis": {
                            "position": [
                                0.0,
                                0.4,
                                0.0
                            ]
                        },
                        "catapult_arm": {
                            "rotation": [
                                -0.35,
                                0.0,
                                0.0,
                                0.94
                            ]
                        }
                    }
                }
            ]
        },
        "move": {
            "duration": 0.5,
            "loop": true,
            "keyframes": [
                {
                    "time": 0.0,
                    "bones": {
                        "chassis": {
                            "position": [
                                0.0,
                                0.4,
                                0.0
                            ],
                            "rotation": [
                                0.0,
                                0.0,
                                0.02,
                                0.9998
                            ]
                        },
                        "wheel_lf": {
                            "rotation": [
                                0.0,
                                0.0,
                                0.0,
                                1.0
                            ]
                        },
                        "wheel_rf": {
                            "rotation": [
                                0.0,
                                0.0,
                                0.0,
                                1.0
                            ]
                        },
                        "wheel_lb": {
                            "rotation": [
                                0.0,
                                0.0,
                                0.0,
                                1.0
                            ]
                        },
                        "wheel_rb": {
                            "rotation": [
                                0.0,
                                0.0,
                                0.0,
                                1.0
                            ]
                        }
                    }
                },
                {
                    "time": 0.125,
                    "bones": {
                        "chassis": {
                            "position": [
                                0.0,
                                0.42,
                                0.0
                            ],
                            "rotation": [
                                0.0,
                                0.0,
                                0.0,
                                1.0
                            ]
                        },
                        "wheel_lf": {
                            "rotation": [
                                0.38,
                                0.0,
                                0.0,
                                0.93
                            ]
                        },
                        "wheel_rf": {
                            "rotation": [
                                0.38,
                                0.0,
                                0.0,
                                0.93
                            ]
                        },
                        "wheel_lb": {
                            "rotation": [
                                0.38,
                                0.0,
                                0.0,
                                0.93
                            ]
                        },
                        "wheel_rb": {
                            "rotation": [
                                0.38,
                                0.0,
                                0.0,
                                0.93
                            ]
                        }
                    }
                },
                {
                    "time": 0.25,
                    "bones": {
                        "chassis": {
                            "position": [
                                0.0,
                                0.4,
                                0.0
                            ],
                            "rotation": [
                                0.0,
                                0.0,
                                -0.02,
                                0.9998
                            ]
                        },
                        "wheel_lf": {
                            "rotation": [
                                0.7,
                                0.0,
                                0.0,
                                0.71
                            ]
                        },
                        "wheel_rf": {
                            "rotation": [
                                0.7,
                                0.0,
                                0.0,
                                0.71
                            ]
                        },
                        "wheel_lb": {
                            "rotation": [
                                0.7,
                                0.0,
                                0.0,
                                0.71
                            ]
                        },
                        "wheel_rb": {
                            "rotation": [
                                0.7,
                                0.0,
                                0.0,
                                0.71
                            ]
                        }
                    }
                },
                {
                    "time": 0.375,
                    "bones": {
                        "chassis": {
                            "position": [
                                0.0,
                                0.42,
                                0.0
                            ],
                            "rotation": [
                                0.0,
                                0.0,
                                0.0,
                                1.0
                            ]
                        },
                        "wheel_lf": {
                            "rotation": [
                                0.93,
                                0.0,
                                0.0,
                                0.38
                            ]
                        },
                        "wheel_rf": {
                            "rotation": [
                                0.93,
                                0.0,
                                0.0,
                                0.38
                            ]
                        },
                        "wheel_lb": {
                            "rotation": [
                                0.93,
                                0.0,
                                0.0,
                                0.38
                            ]
                        },
                        "wheel_rb": {
                            "rotation": [
                                0.93,
                                0.0,
                                0.0,
                                0.38
                            ]
                        }
                    }
                },
                {
                    "time": 0.5,
                    "bones": {
                        "chassis": {
                            "position": [
                                0.0,
                                0.4,
                                0.0
                            ],
                            "rotation": [
                                0.0,
                                0.0,
                                0.02,
                                0.9998
                            ]
                        },
                        "wheel_lf": {
                            "rotation": [
                                1.0,
                                0.0,
                                0.0,
                                0.0
                            ]
                        },
                        "wheel_rf": {
                            "rotation": [
                                1.0,
                                0.0,
                                0.0,
                                0.0
                            ]
                        },
                        "wheel_lb": {
                            "rotation": [
                                1.0,
                                0.0,
                                0.0,
                                0.0
                            ]
                        },
                        "wheel_rb": {
                            "rotation": [
                                1.0,
                                0.0,
                                0.0,
                                0.0
                            ]
                        }
                    }
                }
            ]
        },
        "attack": {
            "duration": 2.0,
            "loop": false,
            "keyframes": [
                {
                    "time": 0.0,
                    "bones": {
                        "catapult_arm": {
                            "rotation": [
                                -0.35,
                                0.0,
                                0.0,
                                0.94
                            ]
                        }
                    }
                },
                {
                    "time": 0.3,
                    "bones": {
                        "catapult_arm": {
                            "rotation": [
                                -0.5,
                                0.0,
                                0.0,
                                0.87
                            ]
                        }
                    }
                },
                {
                    "time": 0.6,
                    "bones": {
                        "catapult_arm": {
                            "rotation": [
                                -0.6,
                                0.0,
                                0.0,
                                0.8
                            ]
                        }
                    }
                },
                {
                    "time": 0.8,
                    "bones": {
                        "catapult_arm": {
                            "rotation": [
                                0.5,
                                0.0,
                                0.0,
                                0.87
                            ]
                        }
                    },
                    "events": [
                        "corpse_launch"
                    ]
                },
                {
                    "time": 1.2,
                    "bones": {
                        "catapult_arm": {
                            "rotation": [
                                0.3,
                                0.0,
                                0.0,
                                0.95
                            ]
                        }
                    }
                },
                {
                    "time": 1.6,
                    "bones": {
                        "catapult_arm": {
                            "rotation": [
                                -0.2,
                                0.0,
                                0.0,
                                0.98
                            ]
                        }
                    }
                },
                {
                    "time": 2.0,
                    "bones": {
                        "catapult_arm": {
                            "rotation": [
                                -0.35,
                                0.0,
                                0.0,
                                0.94
                            ]
                        }
                    }
                }
            ]
        },
        "death": {
            "duration": 2.0,
            "loop": false,
            "keyframes": [
                {
                    "time": 0.0,
                    "bones": {
                        "root": {
                            "position": [
                                0.0,
                                0.0,
                                0.0
                            ],
                            "rotation": [
                                0.0,
                                0.0,
                                0.0,
                                1.0
                            ]
                        }
                    }
                },
                {
                    "time": 0.5,
                    "bones": {
                        "root": {
                            "position": [
                                0.0,
                                -0.1,
                                0.0
                            ],
                            "rotation": [
                                0.0,
                                0.0,
                                0.15,
                                0.99
                            ]
                        }
                    }
                },
                {
                    "time": 1.0,
                    "bones": {
                        "root": {
                            "position": [
                                0.0,
                                -0.2,
                                0.1
                            ],
                            "rotation": [
                                0.1,
                                0.0,
                                0.3,
                                0.95
                            ]
                        }
                    }
                },
                {
                    "time": 1.5,
                    "bones": {
                        "root": {
                            "position": [
                                0.0,
                                -0.3,
                                0.15
                            ],
                            "rotation": [
                                0.15,
                                0.0,
                                0.4,
                                0.9
                            ]
                        }
                    },
                    "events": [
                        "wagon_collapse"
                    ]
                },
                {
                    "time": 2.0,
                    "bones": {
                        "root": {
                            "position": [
                                0.0,
                                -0.4,
                                0.2
                            ],
                            "rotation": [
                                0.2,
                                0.0,
                                0.45,
                                0.87
                            ]
                        }
                    }
                }
            ]
        }
    },
    "animationStateMachine": {
        "initialState": "idle",
        "states": {
            "idle": {
                "animation": "idle",
                "transitions": [
                    {
                        "to": "move",
                        "condition": "isMoving"
                    },
                    {
                        "to": "attack",
                        "condition": "isAttacking"
                    },
                    {
                        "to": "death",
                        "condition": "isDead"
                    }
                ]
            },
            "move": {
                "animation": "move",
                "transitions": [
                    {
                        "to": "idle",
                        "condition": "!isMoving"
                    },
                    {
                        "to": "attack",
                        "condition": "isAttacking"
                    },
                    {
                        "to": "death",
                        "condition": "isDead"
                    }
                ]
            },
            "attack": {
                "animation": "attack",
                "transitions": [
                    {
                        "to": "idle",
                        "condition": "animationComplete && !isMoving"
                    },
                    {
                        "to": "move",
                        "condition": "animationComplete && isMoving"
                    },
                    {
                        "to": "death",
                        "condition": "isDead"
                    }
                ]
            },
            "death": {
                "animation": "death",
                "transitions": []
            }
        }
    },
    "abilities": [
        {
            "id": "get_corpse",
            "name": "Get Corpse",
            "description": "Picks up a nearby corpse for later use.",
            "hotkey": "G",
            "isToggle": false,
            "corpseCapacity": 8
        },
        {
            "id": "drop_corpse",
            "name": "Drop Corpse",
            "description": "Drops all carried corpses at the current location.",
            "hotkey": "D",
            "isToggle": false
        },
        {
            "id": "exhume_corpses",
            "name": "Exhume Corpses",
            "description": "Generates corpses over time when stationary.",
            "hotkey": "E",
            "isToggle": true,
            "corpseInterval": 15.0,
            "isUpgrade": true
        },
        {
            "id": "disease_cloud",
            "name": "Disease Cloud",
            "description": "Attacks leave a cloud of disease that damages enemies over time.",
            "hotkey": "",
            "isToggle": false,
            "isPassive": true,
            "damagePerSecond": 1.5,
            "duration": 90.0,
            "isUpgrade": true
        }
    ],
    "behaviors": {
        "on_spawn": {
            "actions": [
                {
                    "type": "play_sound",
                    "sound": "meat_wagon_ready"
                },
                {
                    "type": "random_say",
                    "texts": [
                        "The wagon is loaded.",
                        "Flesh for the master.",
                        "Ready to deliver."
                    ],
                    "chance": 1.0
                }
            ]
        },
        "on_attack": {
            "actions": [
                {
                    "type": "play_animation",
                    "animation": "attack"
                },
                {
                    "type": "play_sound",
                    "sound": "catapult_launch"
                },
                {
                    "type": "spawn_projectile",
                    "projectile": "diseased_corpse"
                }
            ]
        },
        "on_death": {
            "actions": [
                {
                    "type": "play_animation",
                    "animation": "death"
                },
                {
                    "type": "play_sound",
                    "sound": "wagon_destruction"
                },
                {
                    "type": "spawn_particles",
                    "effect": "wood_debris"
                },
                {
                    "type": "spawn_corpses",
                    "count": 4
                }
            ]
        }
    }
}