{
  "id": "cybernetics_bay",
  "name": "Cybernetics Bay",
  "display_name": "Cybernetics Bay",
  "description": "An advanced research facility for ground unit upgrades. Researches weapon and armor enhancements that affect all ground forces.",
  "race": "aliens",
  "building_type": "tech",
  "tier": 2,
  "classification": ["structure", "tech", "research", "upgrades"],

  "stats": {
    "health": 500,
    "health_regen": 0,
    "shield": 500,
    "shield_regen": 10.0,
    "shield_regen_delay": 10.0,
    "armor": 1,
    "shield_armor": 0
  },

  "production": {
    "build_time": 65,
    "resource_cost": {
      "minerals": 150,
      "vespene": 100
    },
    "requires_worker": true,
    "worker_consumed": true,
    "requirements": ["cyber_core"],
    "power_required": true,
    "hotkey": "Y"
  },

  "unlocks": {
    "units": ["disruptor", "immortal"],
    "upgrades": ["charge", "blink", "resonating_shields"]
  },

  "researches": [
    {
      "id": "ground_weapons_1",
      "name": "Ground Weapons Level 1",
      "description": "Increases ground unit attack damage",
      "cost": {
        "minerals": 100,
        "vespene": 100
      },
      "research_time": 160,
      "damage_bonus": 1,
      "affects": ["ground_units"],
      "hotkey": "W"
    },
    {
      "id": "ground_armor_1",
      "name": "Ground Armor Level 1",
      "description": "Increases ground unit armor",
      "cost": {
        "minerals": 100,
        "vespene": 100
      },
      "research_time": 160,
      "armor_bonus": 1,
      "affects": ["ground_units"],
      "hotkey": "A"
    },
    {
      "id": "shields_1",
      "name": "Plasma Shields Level 1",
      "description": "Increases shield capacity for all units and structures",
      "cost": {
        "minerals": 150,
        "vespene": 150
      },
      "research_time": 180,
      "shield_bonus": 1,
      "affects": ["all"],
      "hotkey": "S"
    },
    {
      "id": "charge",
      "name": "Charge",
      "description": "Zealots gain the Charge ability",
      "cost": {
        "minerals": 100,
        "vespene": 100
      },
      "research_time": 100,
      "affects": ["zealot"],
      "hotkey": "C"
    },
    {
      "id": "blink",
      "name": "Blink",
      "description": "Stalkers gain the Blink ability",
      "cost": {
        "minerals": 150,
        "vespene": 150
      },
      "research_time": 170,
      "affects": ["stalker"],
      "hotkey": "B"
    }
  ],

  "sight": {
    "vision_range": 9
  },

  "footprint": {
    "width": 3,
    "height": 3
  },

  "visuals": {
    "model": "models/aliens/buildings/cybernetics_bay.fbx",
    "texture": "textures/aliens/buildings/cybernetics_bay.png",
    "icon": "icons/aliens/buildings/cybernetics_bay.png",
    "construction_stages": 3,
    "animations": {
      "idle": "anim_idle",
      "researching": "anim_researching"
    },
    "effects": {
      "idle": "fx_cybernetics_bay_idle",
      "researching": "fx_research_active"
    }
  },

  "audio": {
    "complete": "audio/aliens/buildings/cybernetics_bay_complete.ogg",
    "selected": "audio/aliens/buildings/cybernetics_bay_selected.ogg",
    "research_complete": "audio/aliens/buildings/research_complete.ogg",
    "destroyed": "audio/aliens/buildings/cybernetics_bay_destroyed.ogg"
  }
}
